{
  "experience": [
    {
      "where": "PT. Kode Kolektif Indonesia",
      "as": "Mobile Developer",
      "from": "2023",
      "to": "present",
      "project": [
        {
          "link": "",
          "project_name": "Internal Project",
          "what": [
            "Develop mobile application using React Native",
            "Develop a VPN app implement OpenVPN Library"
          ]
        },
        {
          "link": "https://www.instagram.com/p/CxNjTs6xuNL/?hl=id&img_index=2",
          "project_name": "AMCC x Jogja Coding House - Intermediate Class",
          "what": [
            "As a speaker for Intermediate Class Web Programming with ReactJS"
          ]
        },
         {
          "link": "https://www.instagram.com/abp.incubator/p/Czf4mNWPNOC/",
          "project_name": "ABP x Jogja Coding House - StartUp Talk #115",
          "what": [
            "As a speaker for Amikom Bussiness Park Incubator StartUp Talk #115"
          ]
        },
      ]
    },
    {
      "where": "PT. Merkle Inovasi Teknologi",
      "as": "Mobile Developer",
      "from": "2022",
      "to": "2023",
      "project": [
        {
          "link": "",
          "project_name": "HIS - Siloam Hospital",
          "what": [
            "Develop Web App using NextJS",
            "Develop a create patient feature",
            "Slicing design from figma",
            "Integrate api from backend"
          ]
        },
        {
          "link": "",
          "project_name": "DEX v2",
          "what": [
            "Develop a mobile application using React Native",
            "Slicing design from figma",
            "Integrate api from backend"
          ]
        }
      ]
    },
    {
      "where": "PT. Wiratek Solusi Asia",
      "as": "Mobile Developer",
      "from": "2021",
      "to": "2022",
      "project": [
        {
          "link": "https://play.google.com/store/apps/details?id=com.bukitmakmur.op&hl=id&gl=US",
          "project_name": "BUMA",
          "what": [
            "Develop a module for driver behaviour (module)",
            "Slicing design from figma",
            "Integrate api from backend"
          ]
        },
        {
          "link": "https://play.google.com/store/apps/details?id=id.co.hokben.revamp&hl=id&gl=US",
          "project_name": "HokBen",
          "what": [
            "Develop mobile application using React Native (Revamp)",
            "Slicing new design from figma",
            "Integrate api from backend",
            "Implement new e-wallet payment (GoPay and ShopeePay)",
            "Build and Upload to PlayStore and AppStore"
          ]
        }
      ]
    },
    {
      "where": "PT. Kreasi Alam Teknologi",
      "as": "Mobile Developer",
      "from": "2020",
      "to": "2021",
      "project": [
        {
          "link": "https://play.google.com/store/apps/details?id=com.smartm&hl=id&gl=US",
          "project_name": "SMART PLN by (PT. PLN UIT JBTB)",
          "what": [
            "Develop a mobile application using React Native",
            "Slicing design from figma",
            "Integrate api from backend",
            "Build and Upload to PlayStore and AppStore"
          ]
        }
      ]
    }
  ]
}
